{
    "id": "b115b0bae8b538b3cd72769069fe8045591350f51a551b24befbcf36741c6105-part2",
    "url": "https://help.salesforce.com/s/articleView?id=sf.dato_harmonize_parentchild_define.htm&language=en_US&type=5",
    "content": "nullIntegrate and Analyze Marketing Data with Marketing Cloud Intelligence\nTABLE OF CONTENTS\nClose\nClose\nSearch\nSearch\n Integrate and Analyze Marketing Data with Marketing Cloud Intelligence\n Create a Support Ticket for Marketing Cloud Intelligence\n Get Started with Marketing Cloud Intelligence\n Data Model for Marketing Cloud Intelligence\n Uploading Data in Marketing Cloud Intelligence\n Granular Data Center in Marketing Cloud Intelligence\n Dimensions\n Measurements\n Visualize Your Data with Marketing Cloud Intelligence\n Analyze Your Data with Marketing Cloud Intelligence\n Harmonize Your Data\n Harmonize Data with the Harmonization Center\n Parent-Child Connections in Marketing Cloud Intelligence\n Define a Parent Data Stream\n Parent-Child Use Cases\n Fusing Data Between Datasets\n Custom Classifications in Marketing Cloud Intelligence\n Media Transparency Center\n Marketplace Apps and Tools in Marketing Cloud Intelligence\n\nYou are here:\n\nSALESFORCE HELP\nDOCS\nMARKETING CLOUD INTELLIGENCE\nDefine a Parent Data Stream\n\nDefine a parent data stream to determine a connection between two data streams using a shared entity.\n\nREQUIRED USER PERMISSIONS\nUSER PERMISSIONS NEEDED\nTo define a parent data stream:\tAdmin\nOn the Connect & Mix tab, click Data Streams and then Data Streams list.\nSelect the data stream you’re assigning as a parent data stream and click Edit.\nScroll down to Parent Child settings.\nFrom the Parent Data Stream dropdown list, select the data stream to set as the parent data stream.\nTo view the streams in the parent-child data pool, click View All.\nIn the Data Updates Permissions section, determine how your data stream feeds the parent-child dimensional pool with these options:\n\nUpdate Attributes (1) - Updates existing mapped attributes in the parent-child data pool every time the data stream is ingested.\n\nInherit Attributes and Hierarchy (2) - Prevents existing attributes and hierarchies from being updated.\n\nUpdate Attributes and Hierarchy (3) - Updates existing mapped attributes and the media buy, campaign, or site hierarchy in the parent-child data pool at every data ingestion.\n\nNOTE Selecting this option enables the Override Media Buy Hierarchy option in the More Options section and can’t be disabled.\nSave your changes.\nTo apply the changes, the child data stream must be reprocessed. Recreating your data can have major effects on the data. For more information see Re-Process, Re-Run and Re-Create.\nSelect how to reprocess the data, and then click Recreate.\nDID THIS ARTICLE SOLVE YOUR ISSUE?\nLet us know so we can improve!\nYes\nNo\n ",
    "title": "Defining a Parent Data Stream in Marketing Cloud Intelligence",
    "keywords": [
        "parent-child connections",
        "data stream management",
        "marketing cloud intelligence",
        "data ingestion",
        "attribute updates"
    ],
    "links": [
        "https://help.salesforce.com/sfsites/c/resource/HTCommunityCustomJS/HC_TbidAuth.js",
        "https://help.salesforce.com/s/support\",\"target\":\"_self\",\"label\":\"Contact",
        "https://help.salesforce.com/s/articleView?id=sf.datorama.htm&language=en_US&type=5",
        "https://help.salesforce.com/s/articleView?id=sf.dato_getstarted.htm&language=en_US&type=5",
        "https://help.salesforce.com/s/articleView?id=sf.dato_getstarted_getready.htm&language=en_US&type=5",
        "https://help.salesforce.com/s/articleView?id=sf.dato_getstarted_security.htm&language=en_US&type=5",
        "https://help.salesforce.com/s/articleView?id=sf.dato_getstarted_security_mfa.htm&language=en_US&type=5",
        "https://help.salesforce.com/s/articleView?id=sf.dato_getstarted_security_sso.htm&language=en_US&type=5",
        "https://help.salesforce.com/s/articleView?id=sf.dato_getstarted_cookies.htm&language=en_US&type=5",
        "https://help.salesforce.com/s/articleView?id=sf.dato_getstarted_accounts.htm&language=en_US&type=5",
        "https://help.salesforce.com/s/articleView?id=sf.dato_getstarted_manage_acc_analytics.htm&language=en_US&type=5",
        "https://help.salesforce.com/s/articleView?id=sf.dato_getstarted_manage_data_usage.htm&language=en_US&type=5",
        "https://help.salesforce.com/s/articleView?id=sf.dato_getstarted_setup_customize.htm&language=en_US&type=5",
        "https://help.salesforce.com/s/articleView?id=sf.dato_getstarted_manage_activity_log.htm&language=en_US&type=5",
        "https://help.salesforce.com/s/articleView?id=sf.dato_getstarted_customize_exchange_rates.htm&language=en_US&type=5",
        "https://help.salesforce.com/s/articleView?id=sf.dato_getstarted_manage_users.htm&language=en_US&type=5",
        "https://help.salesforce.com/s/articleView?id=sf.dato_getstarted_customize_collperms.htm&language=en_US&type=5",
        "https://help.salesforce.com/s/articleView?id=sf.dato_getstarted_token_api.htm&language=en_US&type=5",
        "https://help.salesforce.com/s/articleView?id=sf.dato_getstarted_user_groups.htm&language=en_US&type=5",
        "https://help.salesforce.com/s/articleView?id=sf.dato_getstarted_user_groups_create.htm&language=en_US&type=5",
        "https://help.salesforce.com/s/articleView?id=sf.dato_getstarted_customize_collpers_groups.htm&language=en_US&type=5",
        "https://help.salesforce.com/s/articleView?id=sf.dato_getstarted_wspace.htm&language=en_US&type=5",
        "https://help.salesforce.com/s/articleView?id=sf.dato_getstarted_wspace_manage.htm&language=en_US&type=5",
        "https://help.salesforce.com/s/articleView?id=sf.dato_getstarted_wspace_share.htm&language=en_US&type=5",
        "https://help.salesforce.com/s/articleView?id=sf.dato_getstarted_archiving.htm&language=en_US&type=5",
        "https://help.salesforce.com/s/articleView?id=sf.dato_getstarted_wspace_events.htm&language=en_US&type=5",
        "https://help.salesforce.com/s/articleView?id=sf.dato_getstarted_custom_date_range.htm&language=en_US&type=5",
        "https://help.salesforce.com/s/articleView?id=sf.dato_getstarted_ws_int.htm&language=en_US&type=5",
        "https://help.salesforce.com/s/articleView?id=sf.dato_getstarted_ws_int_slack.htm&language=en_US&type=5",
        "https://help.salesforce.com/s/articleView?id=sf.dato_getstarted_sbox.htm&language=en_US&type=5",
        "https://help.salesforce.com/s/articleView?id=sf.dato_getstarted_sbox_mode.htm&language=en_US&type=5",
        "https://help.salesforce.com/s/articleView?id=sf.dato_data_model.htm&language=en_US&type=5",
        "https://help.salesforce.com/s/articleView?id=sf.dato_data_stream_types.htm&language=en_US&type=5",
        "https://help.salesforce.com/s/articleView?id=sf.dato_data_classifcation_data_stream.htm&language=en_US&type=5",
        "https://help.salesforce.com/s/articleView?id=sf.dato_data_stream_types_comp.htm&language=en_US&type=5",
        "https://help.salesforce.com/s/articleView?id=sf.dato_data_stream_types_crm.htm&language=en_US&type=5",
        "https://help.salesforce.com/s/articleView?id=sf.dato_data_jobs_stream_type.htm&language=en_US&type=5",
        "https://help.salesforce.com/s/articleView?id=sf.dato_data_stream_types_ecomm.htm&language=en_US&type=5",
        "https://help.salesforce.com/s/articleView?id=sf.dato_data_stream_types_generic.htm&language=en_US&type=5",
        "https://help.salesforce.com/s/articleView?id=sf.dato_data_stream_types_messaging.htm&language=en_US&type=5",
        "https://help.salesforce.com/s/articleView?id=sf.dato_data.htm&language=en_US&type=5",
        "https://help.salesforce.com/s/articleView?id=sf.dato_data_streams.htm&language=en_US&type=5",
        "https://help.salesforce.com/s/articleView?id=sf.dato_data_streams_tc.htm&language=en_US&type=5",
        "https://help.salesforce.com/s/articleView?id=sf.dato_data_streams_tc_transformers.htm&language=en_US&type=5",
        "https://help.salesforce.com/s/articleView?id=sf.dato_data_streams_tc_transformers_transpose.htm&language=en_US&type=5",
        "https://help.salesforce.com/s/articleView?id=sf.dato_data_streams_api.htm&language=en_US&type=5",
        "https://help.salesforce.com/s/articleView?id=sf.dato_data_streams_api_update.htm&language=en_US&type=5",
        "https://help.salesforce.com/s/articleView?id=sf.dato_data_source_auth.htm&language=en_US&type=5",
        "https://help.salesforce.com/s/articleView?id=sf.dato_data_streams_api_connect.htm&language=en_US&type=5",
        "https://help.salesforce.com/s/articleView?id=sf.dato_data_streams_api_connect_amznbrand.htm&language=en_US&type=5",
        "https://help.salesforce.com/s/articleView?id=sf.dato_data_streams_api_connect_amznseller.htm&language=en_US&type=5",
        "https://help.salesforce.com/s/articleView?id=sf.dato_data_streams_api_connect_amznvendor.htm&language=en_US&type=5",
        "https://help.salesforce.com/s/articleView?id=sf.dato_data_streams_api_connect_acclytics.htm&language=en_US&type=5",
        "https://help.salesforce.com/s/articleView?id=sf.dato_data_streams_api_connect_bing.htm&language=en_US&type=5",
        "https://help.salesforce.com/s/articleView?id=sf.dato_data_streams_api_connect_fb.htm&language=en_US&type=5",
        "https://help.salesforce.com/s/articleView?id=sf.dato_data_streams_api_connect_fbcustom.htm&language=en_US&type=5",
        "https://help.salesforce.com/s/articleView?id=sf.dato_data_streams_api_connect_fbpage.htm&language=en_US&type=5",
        "https://help.salesforce.com/s/articleView?id=sf.dato_data_streams_api_connect_fbpost.htm&language=en_US&type=5",
        "https://help.salesforce.com/s/articleView?id=sf.dato_data_streams_api_connect_gads.htm&language=en_US&type=5",
        "https://help.salesforce.com/s/articleView?id=sf.dato_data_streams_api_connect_gads_custom.htm&language=en_US&type=5",
        "https://help.salesforce.com/s/articleView?id=sf.dato_data_streams_api_connect_ganal.htm&language=en_US&type=5",
        "https://help.salesforce.com/s/articleView?id=sf.dato_data_streams_api_connect_ganal_create.htm&language=en_US&type=5",
        "https://help.salesforce.com/s/articleView?id=sf.dato_data_streams_api_connect_ganal_custom.htm&language=en_US&type=5",
        "https://help.salesforce.com/s/articleView?id=sf.dato_data_streams_api_connect_instagram.htm&language=en_US&type=5",
        "https://help.salesforce.com/s/articleView?id=sf.dato_data_streams_api_connect_liads.htm&language=en_US&type=5",
        "https://help.salesforce.com/s/articleView?id=sf.dato_data_streams_api_connect_commcloud.htm&language=en_US&type=5",
        "https://help.salesforce.com/s/articleView?id=sf.dato_data_streams_api_connect_order.htm&language=en_US&type=5",
        "https://help.salesforce.com/s/articleView?id=sf.dato_data_streams_api_connect_tiktok.htm&language=en_US&type=5",
        "https://help.salesforce.com/s/articleView?id=sf.dato_data_streams_api_connect_twit.htm&language=en_US&type=5",
        "https://help.salesforce.com/s/articleView?id=sf.dato_data_streams_api_connect_twitter_ads.htm&language=en_US&type=5",
        "https://help.salesforce.com/s/articleView?id=sf.dato_data_streams_api_connect_yt.htm&language=en_US&type=5",
        "https://help.salesforce.com/s/articleView?id=sf.dato_data_streams_lite.htm&language=en_US&type=5",
        "https://help.salesforce.com/s/articleView?id=sf.dato_data_streams_lite_create.htm&language=en_US&type=5",
        "https://help.salesforce.com/s/articleView?id=sf.dato_data_streams_direct.htm&language=en_US&type=5",
        "https://help.salesforce.com/s/articleView?id=sf.dato_data_connect_api_concept_datacloud.htm&language=en_US&type=5",
        "https://help.salesforce.com/s/articleView?id=sf.dato_data_mapping.htm&language=en_US&type=5",
        "https://help.salesforce.com/s/articleView?id=sf.dato_data_reach_data.htm&language=en_US&type=5",
        "https://help.salesforce.com/s/articleView?id=sf.dato_data_mapping_files_no_date.htm&language=en_US&type=5",
        "https://help.salesforce.com/s/articleView?id=sf.dato_data_mapping_formulas.htm&language=en_US&type=5",
        "https://help.salesforce.com/s/articleView?id=sf.dato_data_mapping_formulas_special_characters_in_java_regex.htm&language=en_US&type=5",
        "https://help.salesforce.com/s/articleView?id=sf.dato_data_mappinggeo.htm&language=en_US&type=5",
        "https://help.salesforce.com/s/articleView?id=sf.dato_data_adv_streams.htm&language=en_US&type=5",
        "https://help.salesforce.com/s/articleView?id=sf.dato_data_adv_streams_history.htm&language=en_US&type=5",
        "https://help.salesforce.com/s/articleView?id=sf.dato_data_adv_streams_refresh.htm&language=en_US&type=5",
        "https://help.salesforce.com/s/articleView?id=sf.dato_data_adv_streams_updates.htm&language=en_US&type=5",
        "https://help.salesforce.com/s/articleView?id=sf.dato_data_adv_streams_rules.htm&language=en_US&type=5",
        "https://help.salesforce.com/s/articleView?id=sf.dato_data_stream_list.htm&language=en_US&type=5",
        "https://help.salesforce.com/s/articleView?id=sf.dato_data_manage.htm&language=en_US&type=5",
        "https://help.salesforce.com/s/articleView?id=sf.dato_data_manage_changes.htm&language=en_US&type=5",
        "https://help.salesforce.com/s/articleView?id=sf.dato_data_prioritize_processing_q.htm&language=en_US&type=5",
        "https://help.salesforce.com/s/articleView?id=sf.dato_data_templates.htm&language=en_US&type=5",
        "https://help.salesforce.com/s/articleView?id=sf.dato_data_mapping_viz.htm&language=en_US&type=5",
        "https://help.salesforce.com/s/articleView?id=sf.dato_data_workflows.htm&language=en_US&type=5",
        "https://help.salesforce.com/s/articleView?id=sf.dato_data_transformation_rule.htm&language=en_US&type=5",
        "https://help.salesforce.com/s/articleView?id=sf.dato_data_transform_group.htm&language=en_US&type=5",
        "https://help.salesforce.com/s/articleView?id=sf.dato_data_lakes.htm&language=en_US&type=5",
        "https://help.salesforce.com/s/articleView?id=sf.dato_data_lakes_create.htm&language=en_US&type=5",
        "https://help.salesforce.com/s/articleView?id=sf.dato_data_lakes_create_tech.htm&language=en_US&type=5",
        "https://help.salesforce.com/s/articleView?id=sf.dato_data_lakes_mapping.htm&language=en_US&type=5",
        "https://help.salesforce.com/s/articleView?id=sf.dato_data_lakes_query.htm&language=en_US&type=5",
        "https://help.salesforce.com/s/articleView?id=sf.dato_data_lakes_visualize.htm&language=en_US&type=5",
        "https://help.salesforce.com/s/articleView?id=sf.dato_data_lakes_sharing.htm&language=en_US&type=5",
        "https://help.salesforce.com/s/articleView?id=sf.dato_data_lakes_deleting.htm&language=en_US&type=5",
        "https://help.salesforce.com/s/articleView?id=sf.dato_dimensions.htm&language=en_US&type=5",
        "https://help.salesforce.com/s/articleView?id=sf.dato_dimensions_calculated.htm&language=en_US&type=5",
        "https://help.salesforce.com/s/articleView?id=sf.dato_pacing_dimensions.htm&language=en_US&type=5",
        "https://help.salesforce.com/s/articleView?id=sf.dato_data_dimension_explorer.htm&language=en_US&type=5",
        "https://help.salesforce.com/s/articleView?id=sf.dato_measurements.htm&language=en_US&type=5",
        "https://help.salesforce.com/s/articleView?id=sf.dato_measure.htm&language=en_US&type=5",
        "https://help.salesforce.com/s/articleView?id=sf.dato_measure_filtered.htm&language=en_US&type=5",
        "https://help.salesforce.com/s/articleView?id=sf.dato_visualize_your_data.htm&language=en_US&type=5",
        "https://help.salesforce.com/s/articleView?id=sf.dato_visualize_getstarted.htm&language=en_US&type=5",
        "https://help.salesforce.com/s/articleView?id=sf.dato_visualize_collections.htm&language=en_US&type=5",
        "https://help.salesforce.com/s/articleView?id=sf.dato_visualize_pages.htm&language=en_US&type=5",
        "https://help.salesforce.com/s/articleView?id=sf.dato_visualize_pages_create_blank.htm&language=en_US&type=5",
        "https://help.salesforce.com/s/articleView?id=sf.dato_visualize_pages_design.htm&language=en_US&type=5",
        "https://help.salesforce.com/s/articleView?id=sf.dato_visualize_pages_app.htm&language=en_US&type=5",
        "https://help.salesforce.com/s/articleView?id=sf.dato_visualize_pages_dash_templates.htm&language=en_US&type=5",
        "https://help.salesforce.com/s/articleView?id=sf.dato_visualize_widgets.htm&language=en_US&type=5",
        "https://help.salesforce.com/s/articleView?id=sf.dato_visualize_widgets_create.htm&language=en_US&type=5",
        "https://help.salesforce.com/s/articleView?id=sf.dato_visualize_widgets_create_filter.htm&language=en_US&type=5",
        "https://help.salesforce.com/s/articleView?id=sf.dato_visualize_widgets_advanced.htm&language=en_US&type=5",
        "https://help.salesforce.com/s/articleView?id=sf.dato_visualize_widgets_advanced_forecasting.htm&language=en_US&type=5",
        "https://help.salesforce.com/s/articleView?id=sf.dato_visualize_widgets_advanced_high_rules.htm&language=en_US&type=5",
        "https://help.salesforce.com/s/articleView?id=sf.dato_visualize_widgets_advanced_casc_filters.htm&language=en_US&type=5",
        "https://help.salesforce.com/s/articleView?id=sf.dato_visualize_widgets_types.htm&language=en_US&type=5",
        "https://help.salesforce.com/s/articleView?id=sf.dato_visualize_widgets_types_chart.htm&language=en_US&type=5",
        "https://help.salesforce.com/s/articleView?id=sf.dato_visualize_widgets_types_interactive.htm&language=en_US&type=5",
        "https://help.salesforce.com/s/articleView?id=sf.dato_visualize_widgets_interactive_switch.htm&language=en_US&type=5",
        "https://help.salesforce.com/s/articleView?id=sf.dato_visualize_widgets_types_element.htm&language=en_US&type=5",
        "https://help.salesforce.com/s/articleView?id=sf.dato_visualize_widgets_element_custom_create.htm&language=en_US&type=5",
        "https://help.salesforce.com/s/articleView?id=sf.dato_visualize_widgets_additional.htm&language=en_US&type=5",
        "https://help.salesforce.com/s/articleView?id=sf.drill_down_hierarchies.htm&language=en_US&type=5",
        "https://help.salesforce.com/s/articleView?id=sf.dato_visualize_share.htm&language=en_US&type=5",
        "https://help.salesforce.com/s/articleView?id=sf.dato_visualize_share_pages.htm&language=en_US&type=5",
        "https://help.salesforce.com/s/articleView?id=sf.dato_visualize_share_widget_slack.htm&language=en_US&type=5",
        "https://help.salesforce.com/s/articleView?id=sf.dato_visualize_share_to_email.htm&language=en_US&type=5",
        "https://help.salesforce.com/s/articleView?id=sf.dato_visualize_share_sched.htm&language=en_US&type=5",
        "https://help.salesforce.com/s/articleView?id=sf.dato_anlyz.htm&language=en_US&type=5",
        "https://help.salesforce.com/s/articleView?id=sf.dato_anlyz_act_cntr.htm&language=en_US&type=5",
        "https://help.salesforce.com/s/articleView?id=sf.dato_anlyz_emi.htm&language=en_US&type=5",
        "https://help.salesforce.com/s/articleView?id=sf.dato_anlyz_goals.htm&language=en_US&type=5",
        "https://help.salesforce.com/s/articleView?id=sf.dato_anlyz_pivot.htm&language=en_US&type=5",
        "https://help.salesforce.com/s/articleView?id=sf.dato_anlyz_reports.htm&language=en_US&type=5",
        "https://help.salesforce.com/s/articleView?id=sf.dato_anlyz_reports_data_create.htm&language=en_US&type=5",
        "https://help.salesforce.com/s/articleView?id=sf.dato_anlyz_reports_configure.htm&language=en_US&type=5",
        "https://help.salesforce.com/s/articleView?id=sf.dato_anlyz_tableau.htm&language=en_US&type=5",
        "https://help.salesforce.com/s/articleView?id=sf.dato_anlyz_tableau_push.htm&language=en_US&type=5",
        "https://help.salesforce.com/s/articleView?id=sf.dato_anlyz_export.htm&language=en_US&type=5",
        "https://help.salesforce.com/s/articleView?id=sf.dato_anlyz_export_create.htm&language=en_US&type=5",
        "https://help.salesforce.com/s/articleView?id=sf.dato_harmonize.htm&language=en_US&type=5",
        "https://help.salesforce.com/s/articleView?id=sf.dato_harmonize_center.htm&language=en_US&type=5",
        "https://help.salesforce.com/s/articleView?id=sf.dato_harmonize_center_naming.htm&language=en_US&type=5",
        "https://help.salesforce.com/s/articleView?id=sf.dato_harmonize_classify.htm&language=en_US&type=5",
        "https://help.salesforce.com/s/articleView?id=sf.dato_harmonize_classify_files.htm&language=en_US&type=5",
        "https://help.salesforce.com/s/articleView?id=sf.dato_harmonize_classify_files_create.htm&language=en_US&type=5",
        "https://help.salesforce.com/s/articleView?id=sf.dato_harmonize_classify_configure.htm&language=en_US&type=5",
        "https://help.salesforce.com/s/articleView?id=sf.dato_harmonize_validate.htm&language=en_US&type=5",
        "https://help.salesforce.com/s/articleView?id=sf.dato_harmonize_validate_fm.htm&language=en_US&type=5",
        "https://help.salesforce.com/s/articleView?id=sf.dato_harmonize_validate_fm_fixing.htm&language=en_US&type=5",
        "https://help.salesforce.com/s/articleView?id=sf.dato_harmonize_parentchild.htm&language=en_US&type=5",
        "https://help.salesforce.com/s/articleView?id=sf.dato_harmonize_fusion.htm&language=en_US&type=5",
        "https://help.salesforce.com/s/articleView?id=sf.dato_harmonize_custom.htm&language=en_US&type=5",
        "https://help.salesforce.com/s/articleView?id=sf.dato_mtc_intro.htm&language=en_US&type=5",
        "https://help.salesforce.com/s/articleView?id=sf.dato_market.htm&language=en_US&type=5",
        "https://help.salesforce.com/s/articleView?id=sf.dato_market_start.htm&language=en_US&type=5",
        "https://help.salesforce.com/s/articleView?id=sf.dato_market_apps.htm&language=en_US&type=5",
        "https://help.salesforce.com/s/articleView?id=sf.dato_market_available_apps.htm&language=en_US&type=5",
        "https://help.salesforce.com/s/articleView?id=sf.dato_market_audience.htm&language=en_US&type=5",
        "https://help.salesforce.com/s/articleView?id=sf.dato_market_customer.htm&language=en_US&type=5",
        "https://help.salesforce.com/s/articleView?id=sf.dato_market_cross.htm&language=en_US&type=5",
        "https://help.salesforce.com/s/articleView?id=sf.dato_market_datadict.htm&language=en_US&type=5",
        "https://help.salesforce.com/s/articleView?id=sf.dato_market_dataready.htm&language=en_US&type=5",
        "https://help.salesforce.com/s/articleView?id=sf.dato_mark_ecomm_app.htm&language=en_US&type=5",
        "https://help.salesforce.com/s/articleView?id=sf.dato_market_optimizer.htm&language=en_US&type=5",
        "https://help.salesforce.com/s/articleView?id=sf.dato_market_email_web_conv.htm&language=en_US&type=5",
        "https://help.salesforce.com/s/articleView?id=sf.dato_market_templates.htm&language=en_US&type=5",
        "https://help.salesforce.com/s/articleView?id=sf.dato_market_lead_gen.htm&language=en_US&type=5",
        "https://help.salesforce.com/s/articleView?id=sf.dato_market_assist.htm&language=en_US&type=5",
        "https://help.salesforce.com/s/articleView?id=sf.dato_market_insights.htm&language=en_US&type=5",
        "https://help.salesforce.com/s/articleView?id=sf.dato_market_media_name_builder.htm&language=en_US&type=5",
        "https://help.salesforce.com/s/articleView?id=sf.dato_mark_media_pacing_app.htm&language=en_US&type=5",
        "https://help.salesforce.com/s/articleView?id=sf.dato_mark_media_planning_center_app.htm&language=en_US&type=5",
        "https://help.salesforce.com/s/articleView?id=sf.dato_mark_media_planning_center_app_run.htm&language=en_US&type=5",
        "https://help.salesforce.com/s/articleView?id=sf.dato_mark_media_planning_center_app_emi_allocator.htm&language=en_US&type=5",
        "https://help.salesforce.com/s/articleView?id=sf.dato_market_mta.htm&language=en_US&type=5",
        "https://help.salesforce.com/s/articleView?id=sf.dato_market_mcemail.htm&language=en_US&type=5",
        "https://help.salesforce.com/s/articleView?id=sf.dato_market_keywords.htm&language=en_US&type=5",
        "https://help.salesforce.com/s/articleView?id=sf.dato_market_social_intel.htm&language=en_US&type=5",
        "https://help.salesforce.com/s/articleView?id=sf.dato_market_wshealthmonitor.htm&language=en_US&type=5",
        "https://help.salesforce.com/s/articleView?id=sf.dato_market_start_manage.htm&language=en_US&type=5",
        "https://help.salesforce.com/s/articleView?id=sf.dato_market_start_manage_share.htm&language=en_US&type=5",
        "https://help.salesforce.com/s/articleView?id=sf.dato_mark_underlying.htm&language=en_US&type=5",
        "https://help.salesforce.com/s/articleView?id=sf.dato_mark_app_app_installation.htm&language=en_US&type=5",
        "https://help.salesforce.com/s/articleView?id=sf.dato_mark_connectors.htm&language=en_US&type=5",
        "https://help.salesforce.com/s/articleView?id=sf.dato_mark_custom_widgets.htm&language=en_US&type=5",
        "https://help.salesforce.com/s/articleView?id=sf.dato_market_dev_portal.htm&language=en_US&type=5",
        "https://help.salesforce.com/s?language=en_US",
        "https://help.salesforce.com/s/articleView?id=sf.dato_data_manage_changes_re.htm&language=en_US&type=5"
    ],
    "embedding": [
        0.4908093512058258,
        0.3462103009223938,
        0.6426060795783997,
        -0.1558372974395752,
        0.3847890794277191,
        -1.235447645187378,
        -0.022133629769086838,
        -0.17932109534740448,
        -0.3325527310371399,
        -0.4406977891921997,
        -0.12721410393714905,
        0.5408710837364197,
        0.031344346702098846,
        -0.40547704696655273,
        0.9419257044792175,
        -0.11553604900836945,
        -0.7775086760520935,
        -0.26246777176856995,
        -0.39166173338890076,
        -0.5279901623725891,
        -0.2713553309440613,
        -0.05658169090747833,
        0.5756083130836487,
        -0.12510618567466736,
        0.025783859193325043,
        -0.07253590226173401,
        -0.8500226140022278,
        -0.6852493286132812,
        -0.4927336573600769,
        -0.11774669587612152,
        0.4153950810432434,
        -0.27772045135498047,
        -0.368921160697937,
        -0.1090184897184372,
        0.7202640771865845,
        -0.6615039706230164,
        -0.33330467343330383,
        1.0588922500610352,
        -0.49435803294181824,
        -0.06636548787355423,
        0.34635886549949646,
        0.2351749986410141,
        -0.5563717484474182,
        0.43314650654792786,
        0.3948022127151489,
        -0.12052729725837708,
        -0.6704801917076111,
        -0.305669367313385,
        0.3590294122695923,
        -0.5348681807518005,
        -1.036474347114563,
        0.37808892130851746,
        -0.12387725710868835,
        0.5696165561676025,
        0.13620087504386902,
        0.06402257084846497,
        -0.2976592481136322,
        -0.15840807557106018,
        0.9187830090522766,
        -0.9586659669876099,
        -0.14478419721126556,
        0.28305214643478394,
        0.24493490159511566,
        0.09320152550935745,
        0.4007761478424072,
        -0.29300984740257263,
        -0.5313671827316284,
        0.37146154046058655,
        0.2321494221687317,
        -0.07909257709980011,
        0.13200366497039795,
        -0.30372872948646545,
        -0.5696273446083069,
        -0.3999902606010437,
        -0.20061267912387848,
        0.32921722531318665,
        1.4350731372833252,
        0.13866132497787476,
        0.22682256996631622,
        0.24441617727279663,
        -0.6137118339538574,
        -0.09160324931144714,
        -0.25538313388824463,
        -0.7506317496299744,
        -0.3803044259548187,
        1.0533571243286133,
        0.05603905767202377,
        0.6658577919006348,
        -0.23564237356185913,
        0.1625390499830246,
        -0.6029430031776428,
        0.7101895809173584,
        0.42460009455680847,
        0.696380615234375,
        0.00545656681060791,
        -0.45028573274612427,
        0.7285581827163696,
        0.14870989322662354,
        -0.013037502765655518,
        0.514735221862793,
        0.16205938160419464,
        -0.26283204555511475,
        -0.3766609728336334,
        -0.013548925518989563,
        1.3784599304199219,
        -0.2351285070180893,
        -0.6594989895820618,
        -1.0266287326812744,
        -0.39347952604293823,
        0.7050431966781616,
        -0.1867605596780777,
        0.45232850313186646,
        -0.23107203841209412,
        -0.35455065965652466,
        -0.3323359787464142,
        -0.7031031250953674,
        0.7597324252128601,
        -0.5890282392501831,
        0.6248902082443237,
        0.053320180624723434,
        0.14216075837612152,
        0.08938810229301453,
        0.6086953282356262,
        0.5624026656150818,
        -0.012819983065128326,
        -0.30543991923332214,
        -0.25070446729660034,
        0.023947473615407944,
        -0.5742533206939697,
        -0.7479409575462341,
        0.4963383078575134,
        1.5053502321243286,
        0.7263013124465942,
        0.38784411549568176,
        -0.42088907957077026,
        0.2654920220375061,
        0.25566208362579346,
        0.1717648059129715,
        0.054243046790361404,
        0.42984703183174133,
        0.4355320930480957,
        -0.19776900112628937,
        0.09683041274547577,
        -0.7547375559806824,
        -0.2213183045387268,
        0.08008116483688354,
        -0.2795117199420929,
        0.10335952043533325,
        0.1856478899717331,
        -0.49827510118484497,
        0.4035986661911011,
        -0.49102887511253357,
        0.37764230370521545,
        -0.38998258113861084,
        -0.7240036725997925,
        0.2554849684238434,
        0.4714345932006836,
        0.5990588665008545,
        -0.16521310806274414,
        0.4701281189918518,
        0.06166023015975952,
        0.4358087182044983,
        0.2678726315498352,
        0.626459538936615,
        0.1349862813949585,
        0.0701112300157547,
        -0.24971574544906616,
        -0.027296893298625946,
        -0.8753134608268738,
        -0.6080018281936646,
        0.015436151996254921,
        -0.11111246049404144,
        -0.1506013423204422,
        -0.3121333122253418,
        1.2656458616256714,
        -0.3516443073749542,
        0.37170836329460144,
        -0.057968154549598694,
        -0.49513906240463257,
        -0.8193583488464355,
        -1.0069186687469482,
        0.43971627950668335,
        -0.45731228590011597,
        0.0016573145985603333,
        0.1560411900281906,
        -0.3149973154067993,
        0.05935784429311752,
        0.026854850351810455,
        0.2089877426624298,
        -0.22295668721199036,
        0.24658092856407166,
        0.9223613739013672,
        -0.07430265843868256,
        0.48425793647766113,
        0.4009355306625366,
        0.23911193013191223,
        0.21599678695201874,
        -0.19225800037384033,
        -0.27791517972946167,
        -0.11081482470035553,
        0.027467377483844757,
        0.3570549190044403,
        0.03494297340512276,
        -0.051180869340896606,
        -0.47303950786590576,
        -0.6814187169075012,
        -0.07457480579614639,
        -0.2644183039665222,
        -0.6467709541320801,
        0.5029020309448242,
        -0.08074218034744263,
        -0.3641470968723297,
        -0.38008588552474976,
        0.11305775493383408,
        -0.6266044974327087,
        -0.0590875968337059,
        0.04353225231170654,
        0.42451101541519165,
        -0.27268826961517334,
        -0.09861975908279419,
        -0.4006561040878296,
        0.3184248208999634,
        0.6540305018424988,
        -0.31472694873809814,
        0.33303120732307434,
        0.06255588680505753,
        -0.04711173102259636,
        -0.6656937003135681,
        -0.23646053671836853,
        -0.1103522852063179,
        0.024497708305716515,
        -0.07345592230558395,
        0.9159345626831055,
        0.05718909949064255,
        -1.0253714323043823,
        -0.3086121678352356,
        0.30561667680740356,
        0.5131358504295349,
        -0.25415778160095215,
        0.8985824584960938,
        0.28889086842536926,
        -0.03769610822200775,
        -0.5643563270568848,
        -0.061074912548065186,
        -0.09138962626457214,
        0.05658043920993805,
        -0.17094765603542328,
        0.060252442955970764,
        -0.1564876139163971,
        0.18223221600055695,
        -0.705950915813446,
        -0.5417658090591431,
        0.7158095240592957,
        -0.1738525927066803,
        0.06350871175527573,
        0.26667049527168274,
        0.4443106949329376,
        -0.7344748973846436,
        -0.2113083451986313,
        -0.42048656940460205,
        -0.092630535364151,
        -0.29795190691947937,
        -0.4067443311214447,
        0.49295902252197266,
        -0.33877089619636536,
        4.481472492218018,
        0.8023179769515991,
        0.4084600508213043,
        -0.28382444381713867,
        0.2949974238872528,
        1.1327122449874878,
        0.19766683876514435,
        -0.48491913080215454,
        0.7596306204795837,
        -0.1692018359899521,
        -0.15497934818267822,
        -0.2620631158351898,
        -0.10024568438529968,
        0.16122475266456604,
        -0.4034481942653656,
        0.4102528691291809,
        -0.28132396936416626,
        -0.014143705368041992,
        0.03315258026123047,
        -0.41128629446029663,
        -1.3331401348114014,
        0.2703744173049927,
        -0.29886192083358765,
        0.2822034955024719,
        0.026897750794887543,
        -0.010382961481809616,
        0.07945822179317474,
        -0.05985443294048309,
        0.2611229121685028,
        -0.3621779680252075,
        -0.29190948605537415,
        -0.7839502096176147,
        0.49037355184555054,
        -0.36732709407806396,
        0.13656717538833618,
        0.4892047941684723,
        0.19196821749210358,
        -0.5435065627098083,
        0.09506607055664062,
        -0.19522909820079803,
        -0.10917331278324127,
        0.012645505368709564,
        -0.6259558200836182,
        -0.11712481081485748,
        -0.0006180517375469208,
        -0.27360841631889343,
        0.011993013322353363,
        0.10228357464075089,
        -0.022539401426911354,
        -0.1931961625814438,
        0.1263996958732605,
        -0.6297139525413513,
        0.4331684410572052,
        -0.8497507572174072,
        -0.5085837841033936,
        -0.24271021783351898,
        0.23615436255931854,
        -0.4174279272556305,
        0.122820183634758,
        0.5298540592193604,
        0.061974577605724335,
        0.7013302445411682,
        -0.7479338049888611,
        0.35288184881210327,
        -0.41649487614631653,
        -0.07043054699897766,
        0.5637267231941223,
        0.13863416016101837,
        0.27185097336769104,
        -0.024397967383265495,
        0.3010522127151489,
        -0.34783828258514404,
        -0.32701292634010315,
        -0.9812954068183899,
        -0.7279057502746582,
        -0.10256288945674896,
        -0.23520837724208832,
        -0.567649781703949,
        0.3557199537754059,
        -1.1777483224868774,
        0.020304836332798004,
        0.4637696146965027,
        -0.16927915811538696,
        -0.7405679225921631,
        0.8977727890014648,
        0.4160429537296295,
        -0.5082862377166748,
        -0.2759944796562195,
        0.009094737470149994,
        0.29339754581451416,
        0.18765053153038025,
        0.4196920096874237,
        -0.3253234028816223,
        -0.5942926406860352,
        0.5357785820960999
    ]
}